LICENSE
README.md
setup.cfg
setup.py
socrata/__init__.py
socrata/_version.py
socrata/approval.py
socrata/authorization.py
socrata/configs.py
socrata/docs.py
socrata/http.py
socrata/input_schema.py
socrata/job.py
socrata/lazy_pool.py
socrata/output_schema.py
socrata/resource.py
socrata/revisions.py
socrata/sources.py
socrata/views.py
socrata/builders/__init__.py
socrata/builders/parse_options.py
socrata/operations/__init__.py
socrata/operations/configured_job.py
socrata/operations/create.py
socrata/operations/operation.py
socrata/operations/utils.py
socrata_py.egg-info/PKG-INFO
socrata_py.egg-info/SOURCES.txt
socrata_py.egg-info/dependency_links.txt
socrata_py.egg-info/requires.txt
socrata_py.egg-info/top_level.txt