Metadata-Version: 1.1
Name: socrata-py
Version: 1.1.13
Summary: SDK For publishing to Socrata
Home-page: https://github.com/socrata/socrata-py
Author: Chris Duranti
Author-email: chris.duranti@socrata.com
License: MIT
Keywords: socrata open-data not-publishing
Platform: UNKNOWN
Classifier: Development Status :: 3 - Alpha
Classifier: Intended Audience :: Developers
Classifier: Topic :: Software Development :: Build Tools
Classifier: License :: OSI Approved :: MIT License
Classifier: Programming Language :: Python :: 3.5
